taejisutil/Config.py
taejisutil/Singleton.py
taejisutil/Util.py
taejisutil/__init__.py
taejisutil-0.1.7.dist-info/METADATA
taejisutil-0.1.7.dist-info/RECORD
taejisutil-0.1.7.dist-info/WHEEL
taejisutil-0.1.7.dist-info/top_level.txt
