Metadata-Version: 2.1
Name: taejisutil
Version: 0.1.7
Summary: utils
Home-page: http://www.mobilechos.com
Author: cheolgi
Author-email: mobilechos@gmail.com
License: MIT
Platform: UNKNOWN
Classifier: Programming Language :: Python :: 3
Classifier: License :: OSI Approved :: MIT License
Classifier: Operating System :: OS Independent
